velar/__init__.py
velar/client.py
velar/exceptions.py
velar/py.typed
velar/dist/index.js
velar/dist/index.js.map
velar/node_modules/.package-lock.json
velar/node_modules/.bin/acorn
velar/node_modules/.bin/ts-node
velar/node_modules/.bin/ts-node-cwd
velar/node_modules/.bin/ts-node-esm
velar/node_modules/.bin/ts-node-script
velar/node_modules/.bin/ts-node-transpile-only
velar/node_modules/.bin/ts-script
velar/node_modules/.bin/tsc
velar/node_modules/.bin/tsserver
velar/node_modules/@cspotcode/source-map-support/LICENSE.md
velar/node_modules/@cspotcode/source-map-support/README.md
velar/node_modules/@cspotcode/source-map-support/browser-source-map-support.js
velar/node_modules/@cspotcode/source-map-support/package.json
velar/node_modules/@cspotcode/source-map-support/register-hook-require.d.ts
velar/node_modules/@cspotcode/source-map-support/register-hook-require.js
velar/node_modules/@cspotcode/source-map-support/register.d.ts
velar/node_modules/@cspotcode/source-map-support/register.js
velar/node_modules/@cspotcode/source-map-support/source-map-support.d.ts
velar/node_modules/@cspotcode/source-map-support/source-map-support.js
velar/node_modules/@jridgewell/resolve-uri/LICENSE
velar/node_modules/@jridgewell/resolve-uri/README.md
velar/node_modules/@jridgewell/resolve-uri/package.json
velar/node_modules/@jridgewell/resolve-uri/dist/resolve-uri.mjs
velar/node_modules/@jridgewell/resolve-uri/dist/resolve-uri.mjs.map
velar/node_modules/@jridgewell/resolve-uri/dist/resolve-uri.umd.js
velar/node_modules/@jridgewell/resolve-uri/dist/resolve-uri.umd.js.map
velar/node_modules/@jridgewell/resolve-uri/dist/types/resolve-uri.d.ts
velar/node_modules/@jridgewell/sourcemap-codec/LICENSE
velar/node_modules/@jridgewell/sourcemap-codec/README.md
velar/node_modules/@jridgewell/sourcemap-codec/package.json
velar/node_modules/@jridgewell/sourcemap-codec/dist/sourcemap-codec.mjs
velar/node_modules/@jridgewell/sourcemap-codec/dist/sourcemap-codec.mjs.map
velar-0.0.3.dist-info/LICENSE
velar-0.0.3.dist-info/METADATA
velar-0.0.3.dist-info/WHEEL
velar-0.0.3.dist-info/top_level.txt
velar-0.0.3.dist-info/RECORD
