Metadata-Version: 2.1
Name: velar
Version: 0.0.3
Summary: Velar - A Library Encode And Decode With Keyword.
Home-page: https://github.com/AyiinXd/velar
Author: AyiinXd
Author-email: ayiinxd0307@gmail.com
License: GNU General Public License v3 (GPLv3)
Project-URL: Bug Tracker, https://github.com/AyiinXd/velar/issues
Project-URL: Documentation, https://velar.tech
Project-URL: Source Code, https://github.com/AyiinXd/velar
Keywords: Encoder,Decoder,Encrypt,Decrypt
Platform: UNKNOWN
Classifier: Programming Language :: Python :: 3
Classifier: Programming Language :: Python :: 3.8
Classifier: Programming Language :: Python :: 3.9
Classifier: Programming Language :: Python :: 3.10
Classifier: Programming Language :: Python :: 3.11
Classifier: Programming Language :: Python :: 3.12
Classifier: License :: OSI Approved :: GNU General Public License v3 (GPLv3)
Classifier: Operating System :: OS Independent
Requires-Python: ~=3.7
License-File: LICENSE
